async_interpreters/__init__.py
async_interpreters/data.py
async_interpreters/params.py
async_interpreters/utils.py
async_interpreters/workers.py
async_interpreters-0.1.4.dist-info/METADATA
async_interpreters-0.1.4.dist-info/WHEEL
async_interpreters-0.1.4.dist-info/licenses/LICENSE
async_interpreters-0.1.4.dist-info/RECORD
