Metadata-Version: 2.3
Name: async-interpreters
Version: 0.1.4
Summary: subinterpreters for asyncio.
Project-URL: Source, https://github.com/yinziyan1206/async-interpreters
Author-email: "ziyan.yin" <408856732@qq.com>
License-File: LICENSE
Classifier: Development Status :: 2 - Pre-Alpha
Classifier: Intended Audience :: Developers
Classifier: License :: OSI Approved :: MIT License
Classifier: Operating System :: OS Independent
Classifier: Programming Language :: Python :: 3.12
Classifier: Programming Language :: Python :: 3.13
Classifier: Programming Language :: Python :: Implementation :: CPython
Requires-Python: >=3.12
Requires-Dist: anyio
